MedShapeNet/__init__.py
MedShapeNet/cli.py
MedShapeNet/main.py
MedShapeNet-0.1.26.dist-info/LICENSE.txt
MedShapeNet-0.1.26.dist-info/METADATA
MedShapeNet-0.1.26.dist-info/WHEEL
MedShapeNet-0.1.26.dist-info/entry_points.txt
MedShapeNet-0.1.26.dist-info/top_level.txt
MedShapeNet-0.1.26.dist-info/RECORD
