Metadata-Version: 2.1
Name: MedShapeNet
Version: 0.1.26
Summary: Python API to connect and work with the MedShapeNet Medical Shapes Database (https://medshapenet.ikim.nrw/)
Home-page: https://github.com/GLARKI/MedShapeNet2.0
Author: Gijs Luijten
License: CC BY-NC-SA 4.0
Classifier: Programming Language :: Python :: 3.8
Classifier: Programming Language :: Python :: 3.9
Classifier: Programming Language :: Python :: 3.10
Classifier: Programming Language :: Python :: 3.11
Classifier: Programming Language :: Python :: 3.12
Classifier: Intended Audience :: Science/Research
Classifier: Topic :: Scientific/Engineering
Classifier: Topic :: Scientific/Engineering :: Mathematics
Classifier: Topic :: Scientific/Engineering :: Medical Science Apps.
Classifier: Topic :: Multimedia :: Graphics :: 3D Modeling
Classifier: Topic :: Scientific/Engineering :: Visualization
Classifier: Topic :: Database
Classifier: Topic :: Database :: Database Engines/Servers
Classifier: Topic :: Software Development :: Libraries :: Python Modules
Requires-Python: >=3.8
License-File: LICENSE.txt
Requires-Dist: minio>=7.2.8
Requires-Dist: tqdm>=4.66.5
Requires-Dist: numpy>=1.18.5
Requires-Dist: numpy-stl>=3.1.2
Requires-Dist: requests>=2.32.3
Requires-Dist: fire>=0.6.0
Requires-Dist: trimesh>=4.4.9
Requires-Dist: pydicom>=2.2.0
Requires-Dist: python-gdcm
Requires-Dist: pygments>=2.4.0
Requires-Dist: jupyter-core>=4.9.2
Requires-Dist: packaging>=17.0
Requires-Dist: traitlets>=5.1.0
